{
  "colors": {
    "background": {
      "content": "#1f1f1f",
      "global": "hsla(240, 0.00%, 18.29%, 1)",
      "input": {
        "@": "hsla(240, 0.00%, 12.00%, 1)",
        "disabled": "hsla(240, 0.00%, 24.57%, 1)",
        "error": "#e38888",
        "focus": "hsla(240, 0.00%, 12.00%, 1)"
      },
      "navigation": "hsla(240, 0.00%, 18.29%, 1)",
      "table": {
        "alt": "hsla(240, 0.00%, 18.29%, 1)",
        "@": "hsla(240, 0.00%, 12.00%, 1)",
        "hover": "hsla(240, 0.00%, 24.57%, 1)",
        "active": {
          "@": "hsla(240, 0.00%, 18.29%, 1)",
          "hover": "hsla(240, 0.00%, 24.57%, 1)"
        },
        "danger": {
          "@": "#ffd4d4",
          "hover": "#e38888"
        },
        "info": {
          "@": "#e1e6f0",
          "hover": "#97b8e9"
        },
        "primary": {
          "@": "#f2f0f5",
          "hover": "#bfa3d4"
        },
        "success": {
          "@": "#f0f7f1",
          "hover": "#91d89f"
        },
        "warning": {
          "@": "#f7f3e9",
          "hover": "#ecd299"
        }
      }
    },
    "border": {
      "input": {
        "@": "hsla(240, 0.00%, 30.86%, 1)",
        "disabled": "hsla(240, 0.00%, 24.57%, 1)",
        "error": "#c84f4f",
        "focus": "#97b8e9"
      },
      "panel": "hsla(240, 0.00%, 24.57%, 1)"
    },
    "brand": {
      "primary": "#ff3633",
      "secondary": "#fff",
      "tertiary": "#1f1f1f"
    },
    "gray": {
      "0": "hsla(240, 0.00%, 12.00%, 1)",
      "10": "hsla(240, 0.00%, 18.29%, 1)",
      "20": "hsla(240, 0.00%, 24.57%, 1)",
      "30": "hsla(240, 0.00%, 30.86%, 1)",
      "40": "hsla(240, 0.00%, 37.14%, 1)",
      "50": "hsla(240, 0.00%, 49.71%, 1)",
      "60": "hsla(240, 0.00%, 62.29%, 1)",
      "70": "hsla(240, 0.00%, 74.86%, 1)",
      "80": "hsla(240, 0.00%, 87.43%, 1)",
      "90": "hsla(240, 0.00%, 100.00%, 1)"
    },
    "text": {
      "primary": "#1f1f1f",
      "secondary": "#fff",
      "link": {
        "@": "#6d3581",
        "hover": "#9a69b3"
      },
      "input": {
        "@": "hsla(240, 0.00%, 87.43%, 1)",
        "disabled": "hsla(240, 0.00%, 62.29%, 1)",
        "error": "#911717",
        "placeholder": "hsla(240, 0.00%, 62.29%, 1)"
      }
    },
    "variant": {
      "transparent": "rgba(0, 0, 0, 0)",
      "danger": {
        "darkest": "#590707",
        "darker": "#750c0c",
        "dark": "#911717",
        "base": "#9e2020",
        "light": "#c84f4f",
        "lighter": "#e38888",
        "lightest": "#ffd4d4"
      },
      "info": {
        "darkest": "#002242",
        "darker": "#043b70",
        "dark": "#10579f",
        "base": "#1b65b3",
        "light": "#5792db",
        "lighter": "#97b8e9",
        "lightest": "#e1e6f0"
      },
      "primary": {
        "darkest": "#270e2e",
        "darker": "#431a4f",
        "dark": "#5f2a70",
        "base": "#6d3581",
        "light": "#9a69b3",
        "lighter": "#bfa3d4",
        "lightest": "#f2f0f5"
      },
      "success": {
        "darkest": "#003d17",
        "darker": "#035c24",
        "dark": "#0d7b34",
        "base": "#158b3e",
        "light": "#4cb96a",
        "lighter": "#91d89f",
        "lightest": "#f0f7f1"
      },
      "warning": {
        "darkest": "#b37e00",
        "darker": "#be8806",
        "dark": "#c99414",
        "base": "#cf9b1f",
        "light": "#e0b859",
        "lighter": "#ecd299",
        "lightest": "#f7f3e9"
      }
    }
  },
  "shadows": {
    "input": "inset 0 1px 1px rgba(0, 0, 0, 0.075), 0 0 8px rgba(87, 146, 219, 0.4)",
    "navigation": "hsla(240, 0.00%, 18.29%, 0.5)",
    "panel": "0 2px 6px 0 hsla(240, 0.00%, 37.14%, 0.4)"
  },
  "elevations": {
    "underneath": "-100",
    "base": "auto",
    "overlay": "100",
    "toast": "200",
    "popup": "300"
  },
  "opacities": {
    "0": 0,
    "35": 0.35,
    "65": 0.65,
    "80": 0.8,
    "100": 1
  },
  "radii": {
    "none": "0",
    "sm": "2px",
    "md": "4px",
    "lg": "6px",
    "round": "50%"
  },
  "spacings": {
    "0": "0px",
    "1": "1px",
    "huge": "8.25rem",
    "xxl": "5.10rem",
    "xl": "3.15rem",
    "lg": "1.95rem",
    "md": "1.20rem",
    "sm": "0.75rem",
    "xs": "0.45rem",
    "xxs": "0.30rem",
    "px": {
      "0": 0,
      "1": 1,
      "huge": 116,
      "xxl": 71,
      "xl": 44,
      "lg": 27,
      "md": 17,
      "sm": 11,
      "xs": 6,
      "xxs": 4
    }
  },
  "typography": {
    "fonts": {
      "sans": "\"Open Sans\", Frutiger, \"Frutiger Linotype\", Univers, Calibri, \"Gill Sans\", \"Gill Sans MT\", \"Myriad Pro\", Myriad, \"DejaVu Sans Condensed\", \"Liberation Sans\", \"Nimbus Sans L\", Tahoma, Geneva, \"Helvetica Neue\", Helvetica, Arial, sans-serif",
      "serif": "Constantia, \"Lucida Bright\", Lucidabright, \"Lucida Serif\", Lucida, \"DejaVu Serif\", \"Bitstream Vera Serif\", \"Liberation Serif\", Georgia, serif",
      "monospace": "\"Roboto Mono\", \"Andale Mono WT\", \"Andale Mono\", \"Lucida Console\", \"Lucida Sans Typewriter\", \"DejaVu Sans Mono\", \"Bitstream Vera Sans Mono\", \"Liberation Mono\", \"Nimbus Mono L\", Menlo, Monaco, \"Courier New\", Courier, monospace"
    },
    "lineHeights": {
      "compact": "0.8",
      "tight": "1",
      "base": "normal",
      "loose": "1.2",
      "relaxed": "1.5"
    },
    "fontRatio": "1.125",
    "fontSizes": {
      "root": "87.5%",
      "base": "1rem",
      "xxs": "calc(calc(calc(1rem * 1.125) / 1.125) / 1.125)",
      "xs": "calc(calc(1rem * 1.125) / 1.125)",
      "sm": "calc(1rem * 1.125)",
      "md": "calc(calc(1rem * 1.125) * 1.125)",
      "lg": "calc(calc(calc(1rem * 1.125) * 1.125) * 1.125)",
      "xl": "calc(calc(calc(calc(1rem * 1.125) * 1.125) * 1.125) * 1.125)",
      "xxl": "calc(calc(calc(calc(calc(1rem * 1.125) * 1.125) * 1.125) * 1.125) * 1.125)",
      "huge": "calc((calc(calc(calc(calc(calc(1rem * 1.125) * 1.125) * 1.125) * 1.125) * 1.125) * 1.5) * 1.125)"
    },
    "fontWeights": {
      "thin": "100",
      "light": "300",
      "regular": "400",
      "medium": "500",
      "semibold": "600",
      "bold": "700",
      "black": "900"
    }
  }
}